HW3-Coverage-Analysis/CAD_HW3/a111204_cpu.v

module ram16x8 (data_out, clk, w_mem, address, data_in);
   
input[3:0] address;
input[7:0] data_in;
input w_mem, clk;
output[7:0] data_out;

reg[7:0] ram_data[16:0];
reg[7:0] data_out;

always@(posedge clk)begin
	if (w_mem == 1'b0)
		data_out = ram_data[address];
	else if(w_mem == 1'b1)
		ram_data[address] = data_in;
	else
		data_out = 8'hz;
end
endmodule

module cpu(out, in, clk, reset);

parameter DATA_IN=0, REG_C_O=1, ALU_OUT=2, MEM_OUT=3;
   
input[7:0] in;
input clk, reset;
output[7:0] out;

reg[7:0] reg_a, reg_b, reg_c, instr, write_data, out;
wire[7:0] in, mem_out, alu_out;
wire clk, reset;
wire [3:0] addr;
wire [1:0] sel;
wire ready, w_out, w_reg_a, w_reg_b, w_reg_c, w_mem;

always@(alu_out or in or mem_out or reg_c or sel)begin
	if (sel == DATA_IN)
		write_data = in;
	else if (sel == ALU_OUT)
		write_data = alu_out;
    else if (sel == MEM_OUT)
        write_data = mem_out;
    else if (sel == REG_C_O)
        write_data = reg_c;
end   
   
always@(posedge clk)begin
	if(reset)begin
		instr = 0;
		reg_a = 0;
		reg_b = 0;
		reg_c = 0;
		out = 0;
	end
	else begin
	    instr = in;
		if(ready)begin
			if (w_reg_c)
				reg_c = write_data;
			else if (w_reg_a)
				reg_a = write_data;
			else if (w_reg_b)
				reg_b = write_data;
			else 
				out = write_data;
		end
	end
end

ram16x8 r1(
	//output
	.data_out	(mem_out[7:0]),
	//input
	.address	(addr[3:0]),
	.data_in	(write_data[7:0]),
	.w_mem		(w_mem),
	.clk		(clk));
   
ALU a1(
	//output
	.alu_out	(alu_out[7:0]),
	//input
	.reg_a		(reg_a[7:0]),
	.reg_b		(reg_b[7:0]),
	.sel_fun	(instr[6:4]));

Control c1(
	//output
	.addr		(addr[3:0]),
	.sel		(sel[1:0]),
	.ready		(ready),
	.w_out		(w_out),
	.w_reg_a	(w_reg_a),
	.w_reg_b	(w_reg_b),
	.w_reg_c	(w_reg_c),
	.w_mem		(w_mem),
	//input
	.opcode		(instr[7:0]),
	.clk		(clk),
	.reset		(reset));
   
endmodule

module Control(opcode, clk, reset, addr, sel, ready,
		w_out, w_reg_a, w_reg_b, w_reg_c, w_mem) ;

parameter DATA_IN=0, REG_C_O=1, ALU_OUT=2, MEM_OUT=3;
parameter ST_0=0, ST_1=1, ST_2=2, ST_3=3;
   
input[7:0] opcode;
input clk, reset;
output[3:0] addr;
output[1:0] sel;
output ready, w_out, w_reg_a, w_reg_b, w_reg_c, w_mem;

reg[3:0] addr;
reg[1:0] sel;
reg ready, w_mem, w_out, w_reg_a, w_reg_b, w_reg_c;
reg[1:0] current_state, next_state;
   
always@(posedge clk)begin
	if (!reset)
		current_state = next_state;
	else
		current_state = ST_1;
	end

always@(current_state or opcode)begin
	case(current_state)
	ST_0:begin
		ready = 1;
		addr = opcode[3:0];
		case (opcode[7:4])
		4'b0000:begin // C = A + B [1 cycle]
				w_out=0; w_reg_a=0; w_reg_b=0; w_reg_c=1; w_mem=0;
				sel=ALU_OUT; next_state=ST_0; 
				end
		4'b0001:begin // C = A - B [1 cycle]
				w_out=0; w_reg_a=0; w_reg_b=0; w_reg_c=1; w_mem=0; 
				sel=ALU_OUT; next_state=ST_0;
				end
		4'b0010:begin // C = A + 1 [1 cycle]
				w_out=0; w_reg_a=0; w_reg_b=0; w_reg_c=1; w_mem=0; 
				sel=ALU_OUT; next_state=ST_0;
				end
		4'b0011:begin // C = A - 1 [1 cycle]
				w_out=0; w_reg_a=0; w_reg_b=0; w_reg_c=1; w_mem=0; 
				sel=ALU_OUT; next_state=ST_0;
				end
		4'b0100:begin // C = A + B + 1 [1 cycle]
				w_out=0; w_reg_a=0; w_reg_b=0; w_reg_c=1; w_mem=0;
				sel=ALU_OUT; next_state=ST_0;
				end
		4'b0101:begin // C = -A [1 cycle]
				w_out=0; w_reg_a=0; w_reg_b=0; w_reg_c=1; w_mem=0;
				sel=ALU_OUT; next_state=ST_0;
				end
		4'b0110:begin // Input A [2 cycles]
				w_out=0; w_reg_a=1; w_reg_b=0; w_reg_c=0; w_mem=0;
				sel=DATA_IN; next_state=ST_1;
				end
		4'b0111:begin // Input B [2 cycles]
				w_out=0; w_reg_a=0; w_reg_b=1; w_reg_c=0; w_mem=0; 
				sel=DATA_IN; next_state=ST_1;
				end
		4'b1000:begin // Input Mem [2 cycles]
				w_out=0; w_reg_a=0; w_reg_b=0; w_reg_c=0; w_mem=1; 
				sel=DATA_IN; next_state=ST_1;
				end
		4'b1001:begin // Storage C [1 cycle]
				w_out=0; w_reg_a=0; w_reg_b=0; w_reg_c=0; w_mem=1; 
				sel=REG_C_O; next_state=ST_0;
				end
		4'b1010:begin // Load C [2 cycles]
				w_out=0; w_reg_a=0; w_reg_b=0; w_reg_c=0; w_mem=0; 
				sel=MEM_OUT; next_state=ST_2;  
				end
		4'b1011:begin // Ouput C [1 cycle]
				w_out=1; w_reg_a=0; w_reg_b=0; w_reg_c=0; w_mem=0;
				sel=REG_C_O; next_state=ST_0;
				end
		4'b1100:begin // Output Mem [2 cycles]
				w_out=1; w_reg_a=0; w_reg_b=0; w_reg_c=0; w_mem=0; 
				sel=MEM_OUT; next_state=ST_3; 
				end
		4'b1101:begin // A = C [1 cycle]
				w_out=0; w_reg_a=1; w_reg_b=0; w_reg_c=0; w_mem=0;
				sel=REG_C_O; next_state=ST_0; 
				end
		4'b1110:begin // B = C [1 cycle]
				w_out=0; w_reg_a=0; w_reg_b=1; w_reg_c=0; w_mem=0;
				sel=REG_C_O; next_state=ST_0;
				end
		default:begin
				w_out=0; w_reg_a=0; w_reg_b=0; w_reg_c=0; w_mem=1;
				sel=ALU_OUT; next_state=ST_0;
				end
		endcase
	end
	ST_1 : begin
			ready = 0; addr = 0;
			w_out = 0; w_reg_a = 0; w_reg_b = 0; w_reg_c = 0; w_mem = 0;
			sel = DATA_IN; next_state = ST_0;
			end
	ST_2 : begin
			ready = 0; addr = 0;
			w_out = 0; w_reg_a = 0; w_reg_b = 0; w_reg_c = 1; w_mem = 0;
			sel = MEM_OUT; next_state = ST_0;
			end
	ST_3 : begin
			ready = 0; addr = 0;
			w_out = 1; w_reg_a = 0; w_reg_b = 0; w_reg_c = 0; w_mem = 0;
			sel = MEM_OUT; next_state = ST_0;
			end       
	endcase 
end
endmodule

module ALU(alu_out, reg_a, reg_b, sel_fun) ;

input[7:0]  reg_a, reg_b;
input[2:0] 	sel_fun;
output[7:0] alu_out;
reg[7:0] 	alu_out;
   
always@(reg_a or reg_b or sel_fun)begin
	case (sel_fun) 
	3'b000 : alu_out = reg_a + reg_b;
	3'b001 : alu_out = reg_a - reg_b;
	3'b010 : alu_out = reg_a + 1;
	3'b011 : alu_out = reg_a - 1;
	3'b100 : alu_out = reg_a + reg_b + 1;
	3'b101 : alu_out = -reg_a;
	default: alu_out = 8'bx;
	endcase
end
endmodule

HW3-Coverage-Analysis/CAD_HW3/a111204_test.v
module test;

reg[7:0] in;
reg clk,reset;
wire[7:0] out;

initial begin
	clk=0;
	forever
    #5 clk = !clk;
end

initial begin
    $dumpfile("cpu.vcd");
    $dumpvars;	
end

cpu cc(.in(in), .clk(clk), .reset(reset), .out(out));

initial begin
	in    =8'b00000000;
	reset =1'b1;

//write your test pattern----------------

#20 in    =8'b01100111;     //input RegA 0111
	reset =1'b0;

#20 in    =8'b01101000;     //input RegA 0111
	reset =1'b0;

#20 in    =8'b01110001;     //input RegB 0001
	reset =1'b0;

#20 in    =8'b01111110;     //input RegB 0001
	reset =1'b0;

#20 in    =8'b00000000;     //C = A + B
    reset =1'b0;
    
#20 in    =8'b00010000;     //C = A - B
    reset =1'b0;

#20 in    =8'b00100000;     //C = A + 1
    reset =1'b0;
    
#20 in    =8'b00110000;     //C = A - 1
    reset =1'b0;
    
#20 in    =8'b01000000;     //C = A + B + 1
    reset =1'b0;
    
// --- above ALU --- 

#20 in    =8'b11100000;     // B = C
    reset =1'b0;

#20 in    =8'b01011111;     //C = -A
    reset =1'b0;

#20 in    =8'b10011111; // Storage C
    reset =1'b0;

#20 in    =8'b10101111; // Load C
    reset =1'b0;

#20 in    =8'b00110000;     //C = A - 1
    reset =1'b0;

#20 in    =8'b10011111; // Storage C
    reset =1'b0;

#20 in    =8'b10101111; // Load C
    reset =1'b0;

#20 in    =8'b01011111;     //C = -A
    reset =1'b0;

#20 in    =8'b10011111; // Storage C
    reset =1'b0;

#20 in    =8'b10101111; // Load C
    reset =1'b0;

// ---

#20 in    =8'b00000000;
    reset =1'b1;

#20 in    =8'b00110000;     //C = A - 1
    reset =1'b0;
#20 in    =8'b11010000; // A = C
    reset =1'b0;
#20 in    =8'b01011111;     //C = -A
    reset =1'b0;
#20 in    =8'b11010000; // A = C
    reset =1'b0;

#20 in    =8'b10001111; // memory
    reset =1'b0;

// ---
    
#20 in    =8'b10111111; // Output C
    reset =1'b0;

#20 in    =8'b11001111; // Output Mem
    reset =1'b0;

#20 in    =8'b00000000; 
    reset =1'b0;

#20 in    =8'b11001111; // Output Mem
    reset =1'b0;

#20 in    =8'b00000000; 
    reset =1'b1;
// ---

#20 in    =8'b11111111;
    reset =1'b0;

//----------------------------------------
#10  $finish;

end
endmodule

HW3-Coverage-Analysis/CAD_HW3/cpu.vcd
$date
	Wed Dec  7 20:44:53 2022
$end

$version
	Synopsys VCS version O-2018.09_Full64
$end

$timescale
	1s
$end

$comment Csum: 1 d3ba49bd76ff07e0 $end


$scope module test $end
$var reg 8 ! in [7:0] $end
$var reg 1 " clk $end
$var reg 1 # reset $end
$var wire 8 $ out [7:0] $end

$scope module cc $end
$var wire 8 ! in [7:0] $end
$var wire 1 " clk $end
$var wire 1 # reset $end
$var reg 8 $ out [7:0] $end
$var reg 8 % reg_a [7:0] $end
$var reg 8 & reg_b [7:0] $end
$var reg 8 ' reg_c [7:0] $end
$var reg 8 ( instr [7:0] $end
$var reg 8 ) write_data [7:0] $end
$var wire 8 * mem_out [7:0] $end
$var wire 8 + alu_out [7:0] $end
$var wire 4 , addr [3:0] $end
$var wire 2 - sel [1:0] $end
$var wire 1 . ready $end
$var wire 1 / w_out $end
$var wire 1 0 w_reg_a $end
$var wire 1 1 w_reg_b $end
$var wire 1 2 w_reg_c $end
$var wire 1 3 w_mem $end

$scope module r1 $end
$var wire 4 , address [3:0] $end
$var wire 8 ) data_in [7:0] $end
$var wire 1 3 w_mem $end
$var wire 1 " clk $end
$var reg 8 * data_out [7:0] $end
$upscope $end


$scope module a1 $end
$var wire 8 % reg_a [7:0] $end
$var wire 8 & reg_b [7:0] $end
$var wire 3 4 sel_fun [2:0] $end
$var reg 8 + alu_out [7:0] $end
$upscope $end


$scope module c1 $end
$var wire 8 ( opcode [7:0] $end
$var wire 1 " clk $end
$var wire 1 # reset $end
$var reg 4 , addr [3:0] $end
$var reg 2 - sel [1:0] $end
$var reg 1 . ready $end
$var reg 1 / w_out $end
$var reg 1 0 w_reg_a $end
$var reg 1 1 w_reg_b $end
$var reg 1 2 w_reg_c $end
$var reg 1 3 w_mem $end
$var reg 2 5 current_state [1:0] $end
$var reg 2 6 next_state [1:0] $end
$upscope $end

$upscope $end

$upscope $end

$enddefinitions $end

#0
$dumpvars
x.
x3
x/
x0
x1
x2
0"
1#
bxxxxxxxx +
bxxxx ,
bxx -
bxx 5
bxxxxxxxx *
b00000000 !
bxxxxxxxx (
bxx 6
bxxxxxxxx $
bxxxxxxxx %
bxxxxxxxx &
bxxxxxxxx '
bxxx 4
bxxxxxxxx )
$end
#5
1"
b00000000 (
b000 4
b00000000 %
b00000000 &
b00000000 '
b00000000 $
bzzzzzzzz *
b01 5
0.
b0000 ,
0/
00
01
02
03
b00 -
b00 6
b00000000 +
b00000000 )
#10
0"
#15
1"
bxxxxxxxx *
#20
b01100111 !
0#
0"
b01100111 )
#25
1"
b01100111 (
b110 4
b00 5
1.
b0111 ,
10
b01 6
bxxxxxxxx +
#30
0"
#35
1"
b01100111 %
b01 5
0.
b0000 ,
00
b00 6
#40
b01101000 !
0"
b01101000 )
#45
1"
b01101000 (
b00 5
1.
b1000 ,
10
b01 6
#50
0"
#55
1"
b01101000 %
b01 5
0.
b0000 ,
00
b00 6
#60
b01110001 !
0"
b01110001 )
#65
1"
b01110001 (
b111 4
b00 5
1.
b0001 ,
11
b01 6
#70
0"
#75
1"
b01110001 &
b01 5
0.
b0000 ,
01
b00 6
#80
b01111110 !
0"
b01111110 )
#85
1"
b01111110 (
b00 5
1.
b1110 ,
11
b01 6
#90
0"
#95
1"
b01111110 &
b01 5
0.
b0000 ,
01
b00 6
#100
b00000000 !
0"
b00000000 )
#105
1"
b00000000 (
b000 4
b00 5
1.
12
b10 -
b11100110 +
b11100110 )
#110
0"
#115
1"
b11100110 '
#120
b00010000 !
0"
#125
1"
b00010000 (
b001 4
b11101010 +
b11101010 )
#130
0"
#135
1"
b11101010 '
#140
b00100000 !
0"
#145
1"
b00100000 (
b010 4
b01101001 +
b01101001 )
#150
0"
#155
1"
b01101001 '
#160
b00110000 !
0"
#165
1"
b00110000 (
b011 4
b01100111 +
b01100111 )
#170
0"
#175
1"
b01100111 '
#180
b01000000 !
0"
#185
1"
b01000000 (
b100 4
b11100111 +
b11100111 )
#190
0"
#195
1"
b11100111 '
#200
b11100000 !
0"
#205
1"
b11100000 (
b110 4
11
02
b01 -
bxxxxxxxx +
#210
0"
#215
1"
b11100111 &
#220
b01011111 !
0"
#225
1"
b01011111 (
b101 4
b1111 ,
01
12
b10 -
b10011000 +
b10011000 )
#230
0"
#235
1"
b10011000 '
#240
b10011111 !
0"
#245
1"
b10011111 (
b001 4
02
13
b01 -
b10000001 +
#250
0"
#255
1"
b10011000 $
#260
b10101111 !
0"
#265
1"
b10101111 (
b010 4
03
b11 -
b10 6
b01101001 +
bxxxxxxxx )
#270
0"
#275
1"
bxxxxxxxx $
b10011000 *
b10 5
b10011000 )
0.
b0000 ,
12
b00 6
#280
b00110000 !
0"
#285
1"
b00110000 (
b011 4
bxxxxxxxx *
b00 5
1.
b10 -
b01100111 +
b01100111 )
#290
0"
#295
1"
b01100111 '
#300
b10011111 !
0"
#305
1"
b10011111 (
b001 4
b1111 ,
02
13
b01 -
b10000001 +
#310
0"
#315
1"
b01100111 $
#320
b10101111 !
0"
#325
1"
b10101111 (
b010 4
03
b11 -
b10 6
b01101001 +
bxxxxxxxx )
#330
0"
#335
1"
bxxxxxxxx $
b01100111 *
b10 5
b01100111 )
0.
b0000 ,
12
b00 6
#340
b01011111 !
0"
#345
1"
b01011111 (
b101 4
bxxxxxxxx *
b00 5
1.
b1111 ,
b10 -
b10011000 +
b10011000 )
#350
0"
#355
1"
b10011000 '
b01100111 *
#360
b10011111 !
0"
#365
1"
b10011111 (
b001 4
02
13
b01 -
b10000001 +
#370
0"
#375
1"
b10011000 $
#380
b10101111 !
0"
#385
1"
b10101111 (
b010 4
03
b11 -
b10 6
b01101001 +
b01100111 )
#390
0"
#395
1"
b01100111 $
b10011000 *
b10 5
b10011000 )
0.
b0000 ,
12
b00 6
#400
b00000000 !
1#
0"
#405
1"
b00000000 (
b000 4
b00000000 %
b00000000 &
b00000000 '
b00000000 $
bxxxxxxxx *
b01 5
02
b00 -
b00000000 +
b00000000 )
#410
0"
#415
1"
#420
b00110000 !
0#
0"
b00110000 )
#425
1"
b00110000 (
b011 4
b00 5
1.
12
b10 -
b11111111 +
b11111111 )
#430
0"
#435
1"
b11111111 '
#440
b11010000 !
0"
#445
1"
b11010000 (
b101 4
10
02
b01 -
b00000000 +
#450
0"
#455
1"
b11111111 %
b00000001 +
#460
b01011111 !
0"
#465
1"
b01011111 (
b1111 ,
00
12
b10 -
b00000001 )
#470
0"
#475
1"
b00000001 '
b10011000 *
#480
b11010000 !
0"
#485
1"
b11010000 (
b0000 ,
10
02
b01 -
#490
0"
#495
1"
b00000001 %
bxxxxxxxx *
b11111111 +
#500
b10001111 !
0"
#505
1"
b10001111 (
b000 4
b1111 ,
00
13
b00 -
b01 6
b00000001 +
b10001111 )
#510
0"
#515
1"
b10001111 $
b01 5
0.
b0000 ,
03
b00 6
#520
b10111111 !
0"
b10111111 )
#525
1"
b10111111 (
b011 4
b00 5
1.
b1111 ,
1/
b01 -
b00000000 +
b00000001 )
#530
0"
#535
1"
b00000001 $
b10001111 *
#540
b11001111 !
0"
#545
1"
b11001111 (
b100 4
b11 -
b11 6
b00000010 +
b10001111 )
#550
0"
#555
1"
b10001111 $
b11 5
0.
b0000 ,
b00 6
#560
b00000000 !
0"
#565
1"
b00000000 (
b000 4
bxxxxxxxx *
b00 5
1.
0/
12
b10 -
b00000001 +
b00000001 )
#570
0"
#575
1"
#580
b11001111 !
0"
#585
1"
b11001111 (
b100 4
b1111 ,
1/
02
b11 -
b11 6
b00000010 +
bxxxxxxxx )
#590
0"
#595
1"
bxxxxxxxx $
b10001111 *
b11 5
b10001111 )
0.
b0000 ,
b00 6
#600
b00000000 !
1#
0"
#605
1"
b00000000 (
b000 4
b00000000 %
b00000000 '
b00000000 $
bxxxxxxxx *
b01 5
0/
b00 -
b00000000 +
b00000000 )
#610
0"
#615
1"
#620
b11111111 !
0#
0"
b11111111 )
#625
1"
b11111111 (
b111 4
b00 5
1.
b1111 ,
13
b10 -
bxxxxxxxx +
bxxxxxxxx )
